[{"id":"383","name":"acoustic guitar","catalogueStatus":1,"image":"https://acnhcdn.com/latest/FtrIcon/FtrAcorsticguitar_Remake_0_0.png","variant":{"id":"0_0","name":"Natural"}},{"id":"383","name":"acoustic guitar","catalogueStatus":1,"image":"https://acnhcdn.com/latest/FtrIcon/FtrAcorsticguitar_Remake_1_0.png","variant":{"id":"1_0","name":"Cherry"}},{"id":"383","name":"acoustic guitar","catalogueStatus":1,"image":"https://acnhcdn.com/latest/FtrIcon/FtrAcorsticguitar_Remake_2_0.png","variant":{"id":"2_0","name":"Brown"}},{"id":"383","name":"acoustic guitar","catalogueStatus":1,"image":"https://acnhcdn.com/latest/FtrIcon/FtrAcorsticguitar_Remake_3_0.png","variant":{"id":"3_0","name":"Blue"}},{"id":"383","name":"acoustic guitar","catalogueStatus":1,"image":"https://acnhcdn.com/latest/FtrIcon/FtrAcorsticguitar_Remake_4_0.png","variant":{"id":"4_0","name":"White"}},{"id":"383","name":"acoustic guitar","catalogueStatus":1,"image":"https://acnhcdn.com/latest/FtrIcon/FtrAcorsticguitar_Remake_5_0.png","variant":{"id":"5_0","name":"Black"}},{"id":"383","name":"acoustic guitar","catalogueStatus":1,"image":"https://acnhcdn.com/latest/FtrIcon/FtrAcorsticguitar_Remake_6_0.png","variant":{"id":"6_0","name":"Pink"}},{"id":"3821","name":"air circulator","catalogueStatus":0,"image":"https://acnhcdn.com/latest/FtrIcon/FtrCirculator_Remake_0_0.png","variant":{"id":"0_0","name":"White"}},{"id":"3821","name":"air circulator","catalogueStatus":0,"image":"https://acnhcdn.com/latest/FtrIcon/FtrCirculator_Remake_1_0.png","variant":{"id":"1_0","name":"Black"}},{"id":"3821","name":"air circulator","catalogueStatus":0,"image":"https://acnhcdn.com/latest/FtrIcon/FtrCirculator_Remake_2_0.png","variant":{"id":"2_0","name":"Pink"}},{"id":"3821","name":"air circulator","catalogueStatus":0,"image":"https://acnhcdn.com/latest/FtrIcon/FtrCirculator_Remake_3_0.png","variant":{"id":"3_0","name":"Green"}},{"id":"3821","name":"air circulator","catalogueStatus":0,"image":"https://acnhcdn.com/latest/FtrIcon/FtrCirculator_Remake_4_0.png","variant":{"id":"4_0","name":"Yellow"}},{"id":"846","name":"alto saxophone","catalogueStatus":0,"image":"https://acnhcdn.com/latest/FtrIcon/FtrAltosax.png","variant":null},{"id":"1317","name":"anatomical model","catalogueStatus":0,"image":"https://acnhcdn.com/latest/FtrIcon/FtrAnatomicalmodel.png","variant":null},{"id":"7238","name":"anchor statue","catalogueStatus":1,"image":"https://acnhcdn.com/latest/FtrIcon/FtrShipanchor_Remake_0_0.png","variant":{"id":"0_0","name":"Black"}},{"id":"7238","name":"anchor statue","catalogueStatus":1,"image":"https://acnhcdn.com/latest/FtrIcon/FtrShipanchor_Remake_1_0.png","variant":{"id":"1_0","name":"Silver"}},{"id":"7238","name":"anchor statue","catalogueStatus":1,"image":"https://acnhcdn.com/latest/FtrIcon/FtrShipanchor_Remake_2_0.png","variant":{"id":"2_0","name":"Gold"}},{"id":"7238","name":"anchor statue","catalogueStatus":1,"image":"https://acnhcdn.com/latest/FtrIcon/FtrShipanchor_Remake_3_0.png","variant":{"id":"3_0","name":"White"}},{"id":"7238","name":"anchor statue","catalogueStatus":1,"image":"https://acnhcdn.com/latest/FtrIcon/FtrShipanchor_Remake_4_0.png","variant":{"id":"4_0","name":"Blue"}},{"id":"7238","name":"anchor statue","catalogueStatus":1,"image":"https://acnhcdn.com/latest/FtrIcon/FtrShipanchor_Remake_5_0.png","variant":{"id":"5_0","name":"Retro"}},{"id":"7867","name":"angled signpost","catalogueStatus":1,"image":"https://acnhcdn.com/latest/FtrIcon/FtrSignpostTilt_Remake_0_0.png","variant":{"id":"0_0","name":"Home"}},{"id":"7867","name":"angled signpost","catalogueStatus":1,"image":"https://acnhcdn.com/latest/FtrIcon/FtrSignpostTilt_Remake_1_0.png","variant":{"id":"1_0","name":"Forest"}},{"id":"7867","name":"angled signpost","catalogueStatus":1,"image":"https://acnhcdn.com/latest/FtrIcon/FtrSignpostTilt_Remake_2_0.png","variant":{"id":"2_0","name":"Fishing Spot"}},{"id":"7867","name":"angled signpost","catalogueStatus":1,"image":"https://acnhcdn.com/latest/FtrIcon/FtrSignpostTilt_Remake_3_0.png","variant":{"id":"3_0","name":"Resident Services"}},{"id":"7867","name":"angled signpost","catalogueStatus":1,"image":"https://acnhcdn.com/latest/FtrIcon/FtrSignpostTilt_Remake_4_0.png","variant":{"id":"4_0","name":"Airport"}},{"id":"7867","name":"angled signpost","catalogueStatus":1,"image":"https://acnhcdn.com/latest/FtrIcon/FtrSignpostTilt_Remake_5_0.png","variant":{"id":"5_0","name":"Shop"}},{"id":"7867","name":"angled signpost","catalogueStatus":1,"image":"https://acnhcdn.com/latest/FtrIcon/FtrSignpostTilt_Remake_6_0.png","variant":{"id":"6_0","name":"Tailors"}},{"id":"7867","name":"angled signpost","catalogueStatus":1,"image":"https://acnhcdn.com/latest/FtrIcon/FtrSignpostTilt_Remake_7_0.png","variant":{"id":"7_0","name":"Museum"}},{"id":"3957","name":"antique bed","catalogueStatus":0,"image":"https://acnhcdn.com/latest/FtrIcon/FtrAntiqueBedW_Remake_0_0.png","variant":{"id":"0_0","name":"Brown"}},{"id":"3957","name":"antique bed","catalogueStatus":0,"image":"https://acnhcdn.com/latest/FtrIcon/FtrAntiqueBedW_Remake_1_0.png","variant":{"id":"1_0","name":"Natural"}},{"id":"3957","name":"antique bed","catalogueStatus":0,"image":"https://acnhcdn.com/latest/FtrIcon/FtrAntiqueBedW_Remake_2_0.png","variant":{"id":"2_0","name":"Black"}},{"id":"3956","name":"antique bureau","catalogueStatus":0,"image":"https://acnhcdn.com/latest/FtrIcon/FtrAntiqueBureau_Remake_0_0.png","variant":{"id":"0_0","name":"Brown"}},{"id":"3956","name":"antique bureau","catalogueStatus":0,"image":"https://acnhcdn.com/latest/FtrIcon/FtrAntiqueBureau_Remake_1_0.png","variant":{"id":"1_0","name":"Natural"}},{"id":"3956","name":"antique bureau","catalogueStatus":0,"image":"https://acnhcdn.com/latest/FtrIcon/FtrAntiqueBureau_Remake_2_0.png","variant":{"id":"2_0","name":"Black"}},{"id":"3950","name":"antique chair","catalogueStatus":0,"image":"https://acnhcdn.com/latest/FtrIcon/FtrAntiqueChairS_Remake_0_0.png","variant":{"id":"0_0","name":"Brown"}},{"id":"3950","name":"antique chair","catalogueStatus":0,"image":"https://acnhcdn.com/latest/FtrIcon/FtrAntiqueChairS_Remake_1_0.png","variant":{"id":"1_0","name":"Natural"}},{"id":"3950","name":"antique chair","catalogueStatus":0,"image":"https://acnhcdn.com/latest/FtrIcon/FtrAntiqueChairS_Remake_2_0.png","variant":{"id":"2_0","name":"Black"}},{"id":"3954","name":"antique clock","catalogueStatus":0,"image":"https://acnhcdn.com/latest/FtrIcon/FtrAntiqueClock_Remake_0_0.png","variant":{"id":"0_0","name":"Brown"}},{"id":"3954","name":"antique clock","catalogueStatus":0,"image":"https://acnhcdn.com/latest/FtrIcon/FtrAntiqueClock_Remake_1_0.png","variant":{"id":"1_0","name":"Natural"}},{"id":"3954","name":"antique clock","catalogueStatus":0,"image":"https://acnhcdn.com/latest/FtrIcon/FtrAntiqueClock_Remake_2_0.png","variant":{"id":"2_0","name":"Black"}},{"id":"3951","name":"antique console table","catalogueStatus":0,"image":"https://acnhcdn.com/latest/FtrIcon/FtrAntiqueConsole_Remake_0_0.png","variant":{"id":"0_0","name":"Brown"}},{"id":"3951","name":"antique console table","catalogueStatus":0,"image":"https://acnhcdn.com/latest/FtrIcon/FtrAntiqueConsole_Remake_1_0.png","variant":{"id":"1_0","name":"Natural"}},{"id":"3951","name":"antique console table","catalogueStatus":0,"image":"https://acnhcdn.com/latest/FtrIcon/FtrAntiqueConsole_Remake_2_0.png","variant":{"id":"2_0","name":"Black"}},{"id":"3958","name":"antique mini table","catalogueStatus":0,"image":"https://acnhcdn.com/latest/FtrIcon/FtrAntiqueTableS_Remake_0_0.png","variant":{"id":"0_0","name":"Brown"}},{"id":"3958","name":"antique mini table","catalogueStatus":0,"image":"https://acnhcdn.com/latest/FtrIcon/FtrAntiqueTableS_Remake_1_0.png","variant":{"id":"1_0","name":"Natural"}},{"id":"3958","name":"antique mini table","catalogueStatus":0,"image":"https://acnhcdn.com/latest/FtrIcon/FtrAntiqueTableS_Remake_2_0.png","variant":{"id":"2_0","name":"Black"}},{"id":"3952","name":"antique table","catalogueStatus":0,"image":"https://acnhcdn.com/latest/FtrIcon/FtrAntiqueTableL_Remake_0_0.png","variant":{"id":"0_0","name":"Brown"}},{"id":"3952","name":"antique table","catalogueStatus":0,"image":"https://acnhcdn.com/latest/FtrIcon/FtrAntiqueTableL_Remake_1_0.png","variant":{"id":"1_0","name":"Natural"}},{"id":"3952","name":"antique table","catalogueStatus":0,"image":"https://acnhcdn.com/latest/FtrIcon/FtrAntiqueTableL_Remake_2_0.png","variant":{"id":"2_0","name":"Black"}},{"id":"3955","name":"antique vanity","catalogueStatus":0,"image":"https://acnhcdn.com/latest/FtrIcon/FtrAntiqueDresser_Remake_0_0.png","variant":{"id":"0_0","name":"Brown"}},{"id":"3955","name":"antique vanity","catalogueStatus":0,"image":"https://acnhcdn.com/latest/FtrIcon/FtrAntiqueDresser_Remake_1_0.png","variant":{"id":"1_0","name":"Natural"}},{"id":"3955","name":"antique vanity","catalogueStatus":0,"image":"https://acnhcdn.com/latest/FtrIcon/FtrAntiqueDresser_Remake_2_0.png","variant":{"id":"2_0","name":"Black"}},{"id":"3959","name":"antique wardrobe","catalogueStatus":0,"image":"https://acnhcdn.com/latest/FtrIcon/FtrAntiqueChest_Remake_0_0.png","variant":{"id":"0_0","name":"Brown"}},{"id":"3959","name":"antique wardrobe","catalogueStatus":0,"image":"https://acnhcdn.com/latest/FtrIcon/FtrAntiqueChest_Remake_1_0.png","variant":{"id":"1_0","name":"Natural"}},{"id":"3959","name":"antique wardrobe","catalogueStatus":0,"image":"https://acnhcdn.com/latest/FtrIcon/FtrAntiqueChest_Remake_2_0.png","variant":{"id":"2_0","name":"Black"}},{"id":"4134","name":"apple chair","catalogueStatus":1,"image":"https://acnhcdn.com/latest/FtrIcon/FtrFruitsChairApple_Remake_0_0.png","variant":{"id":"0_0","name":"Red apple"}},{"id":"4134","name":"apple chair","catalogueStatus":1,"image":"https://acnhcdn.com/latest/FtrIcon/FtrFruitsChairApple_Remake_1_0.png","variant":{"id":"1_0","name":"Green apple"}},{"id":"5956","name":"Aquarius urn","catalogueStatus":1,"image":"https://acnhcdn.com/latest/FtrIcon/FtrZodiacAquarius.png","variant":null},{"id":"8226","name":"arcade combat game","catalogueStatus":0,"image":"https://acnhcdn.com/latest/FtrIcon/FtrArcadegameShooting.png","variant":null},{"id":"8225","name":"arcade fighting game","catalogueStatus":0,"image":"https://acnhcdn.com/latest/FtrIcon/FtrArcadegameFight.png","variant":null},{"id":"8227","name":"arcade mahjong game","catalogueStatus":0,"image":"https://acnhcdn.com/latest/FtrIcon/FtrArcadegameMahjong.png","variant":null},{"id":"12207","name":"arcade seat","catalogueStatus":0,"image":"https://acnhcdn.com/latest/FtrIcon/FtrGameChair_Remake_0_0.png","variant":{"id":"0_0","name":"Red"}},{"id":"12207","name":"arcade seat","catalogueStatus":0,"image":"https://acnhcdn.com/latest/FtrIcon/FtrGameChair_Remake_1_0.png","variant":{"id":"1_0","name":"Gray"}},{"id":"12207","name":"arcade seat","catalogueStatus":0,"image":"https://acnhcdn.com/latest/FtrIcon/FtrGameChair_Remake_2_0.png","variant":{"id":"2_0","name":"Blue"}},{"id":"5954","name":"Aries rocking chair","catalogueStatus":1,"image":"https://acnhcdn.com/latest/FtrIcon/FtrZodiacAries.png","variant":null}]